FASTA_parser/__init__.py
FASTA_parser/command_line.py
FASTA_parser/fasta.py
fasta_parser/__init__.py
fasta_parser/fasta.py
fasta_parser-0.2.dist-info/METADATA
fasta_parser-0.2.dist-info/RECORD
fasta_parser-0.2.dist-info/WHEEL
fasta_parser-0.2.dist-info/top_level.txt
